{
    "configurations": [
        {
            "name": "Linux",
            "includePath": [
                "${workspaceFolder}/**",
                "${workspaceFolder}/build/linux/_deps/cpr-src/include",
                "${workspaceFolder}/build/linux/_deps/nlohmann_json-src/include",
                "${workspaceFolder}/build/linux/_deps/sqlitecpp-src/include"
            ],
            "defines": [],
            "compilerPath": "/usr/bin/clang",
            "cStandard": "c17",
            "cppStandard": "c++17",
            "intelliSenseMode": "linux-clang-x64"
        }
    ],
    "version": 4
}
